aiothingy/__init__.py
aiothingy-0.0.3.dist-info/licenses/LICENSE
aiothingy-0.0.3.dist-info/METADATA
aiothingy-0.0.3.dist-info/WHEEL
aiothingy-0.0.3.dist-info/top_level.txt
aiothingy-0.0.3.dist-info/RECORD
