Metadata-Version: 2.4
Name: aiothingy
Version: 0.0.3
Summary: Asynchronous Python library for interacting with the Nordic Thingy52 over Bluetooth
Home-page: https://github.com/wybiral/aiothingy
Author: davy wybiral
Author-email: davy.wybiral@gmail.com
License: MIT
Classifier: Programming Language :: Python :: 3
Classifier: License :: OSI Approved :: MIT License
Classifier: Operating System :: OS Independent
License-File: LICENSE
Requires-Dist: bleak
Dynamic: author
Dynamic: author-email
Dynamic: classifier
Dynamic: description
Dynamic: description-content-type
Dynamic: home-page
Dynamic: license
Dynamic: license-file
Dynamic: requires-dist
Dynamic: summary
